setup.py
pmigrate/__init__.py
pmigrate/cli.py
pmigrate/lib.py
pmigrate/parse.py
pmigrate.egg-info/PKG-INFO
pmigrate.egg-info/SOURCES.txt
pmigrate.egg-info/dependency_links.txt
pmigrate.egg-info/entry_points.txt
pmigrate.egg-info/requires.txt
pmigrate.egg-info/top_level.txt