Metadata-Version: 1.0
Name: pmigrate
Version: 0.0.1
Summary: A Postgres-specific tool for versioning your DB schema.
Home-page: https://github.com/btubbs/pmigrate
Author: Brent Tubbs
Author-email: brent.tubbs@gmail.com
License: UNKNOWN
Platform: UNKNOWN
